dbupgrade/__init__.py
dbupgrade/__main__.py
dbupgrade/apply.py
dbupgrade/args.py
dbupgrade/db.py
dbupgrade/files.py
dbupgrade/filter.py
dbupgrade/main.py
dbupgrade/py.typed
dbupgrade/result.py
dbupgrade/sql.py
dbupgrade/sql_file.py
dbupgrade/upgrade.py
dbupgrade/url.py
dbupgrade/version.py
dbupgrade-2025.5.0.dist-info/LICENSE
dbupgrade-2025.5.0.dist-info/METADATA
dbupgrade-2025.5.0.dist-info/WHEEL
dbupgrade-2025.5.0.dist-info/entry_points.txt
dbupgrade-2025.5.0.dist-info/RECORD
