Metadata-Version: 2.3
Name: dbupgrade
Version: 2025.5.0
Summary: Database Migration Tool
License: MIT
Author: Sebastian Rittau
Author-email: srittau@rittau.biz
Requires-Python: >=3.10
Classifier: Development Status :: 5 - Production/Stable
Classifier: Environment :: Console
Classifier: Intended Audience :: Developers
Classifier: Topic :: Database
Classifier: Topic :: Software Development
Requires-Dist: sqlalchemy (>=1.4,<3)
Requires-Dist: sqlparse (>=0.3.0)
Project-URL: Bug Tracker, https://github.com/srittau/dbupgrade/issues
Project-URL: Changes, https://github.com/srittau/dbupgrade/blob/main/CHANGELOG.md
Project-URL: GitHub, https://github.com/srittau/dbupgrade
Project-URL: Homepage, https://github.com/srittau/dbupgrade
Project-URL: Repository, https://github.com/srittau/dbupgrade
